[
  {
    "mood": "happy",
    "keywords": [
      "happy",
      "jolly",
      "spring",
      "summer"
    ],
    "special_word": {
      "have a good day": "You look so happy, enjoy some jolly songs",
      "i have a good day": "You look so happy, enjoy some jolly songs",
      "have a nice day": "You look so happy, enjoy some jolly songs",
      "i have a nice day": "You look so happy, enjoy some jolly songs"
    },
    "songs": [
      "Young & Free",
      "Feel Good Indie Rock",
      "Mood Booster",
      "Happy Hits!",
      "Confidence Boost",
      "Just Smile",
      "The Happy Hipster",
      "Sunny Side Up",
      "Seize the Day!",
      "warm hearts feel good",
      "Spring Forward",
      "Who Run The World? Girls."
    ]
  },
  {
    "mood": "coffee",
    "keywords": [
      "coffee",
      "caffeine",
      "coffeetime",
      "cafe"
    ],
    "special_word": {
      "i am in cafe":"Enjoy your life a little bit, searching track for you.",
      "im in cafe":"Enjoy your life a little bit, searching track for you.",
      "im drinking coffee":"Enjoy your life a little bit, searching track for you.",
      "good afternoon":"Enjoy your life a little bit, searching track for you."
    },
    "songs": [
      "Soul Coffee",
      "House Relax",
      "Your Favorite Coffeehouse",
      "Your Coffee Break",
      "NaNoWriMo"
    ]
  },
  {
    "mood": "morning",
    "keywords": [
      "morning",
      "sunny",
      "sunshine",
      "cafe"
    ],
    "special_word": {
      "good morning":"Have a nice day, let’s enjoy some music.",
      "good morning vinci":"Have a nice day, let’s enjoy some music.",
      "today is a sunny day":"Have a nice day, let’s enjoy some music."
    },
    "songs": [
      "Smooth Morning",
      "Morning Rhythm",
      "Ready for the Day",
      "Beat Down Your Morning",
      "Tropical Morning"
    ]
  },
  {
    "mood": "sad",
    "keywords": [
      "sad",
      "lonely",
      "heartbreak"
    ],
    "special_word": {
      "miss my friends":"Cheer up, let’s enjoy some music.",
      "miss my boyfriend":"Cheer up, let’s enjoy some music.",
      "miss my girlfriend":"Cheer up, let’s enjoy some music.",
      "I am lonely":"Cheer up, let’s enjoy some music.",
      "I want cry":"Cheer up, let’s enjoy some music.",
      "I am crying":"Cheer up, let’s enjoy some music.",
      "I am so sad":"Cheer up, let’s enjoy some music.",
      "My heart just broke up":"Cheer up, let’s enjoy some music."
    },
    "songs": [
      "Acoustic Winter",
      "Melancholia",
      "Deep Dark Indie",
      "Forever Alone",
      "The Cure for Loneliness",
      "Coping With Loss",
      "Last One Awake",
      "Deep Dark Indie Folk"
    ]
  },
  {
    "mood": "angry",
    "keywords":[
      "angry"
    ],
    "special_word": {
      "I am so angry": "OK, maybe you should listen to some music.",
      "I'm so angry": "OK, maybe you should listen to some music.",
      "I don’t want to do anything": "OK, maybe you should listen to some music.",
      "I hate everything": "OK, maybe you should listen to some music."
    },
    "songs": [
      "Dark & Stormy",
      "Femme Fatale",
      "SHOEGAZE"
    ]
  }
]
